InsurAutoML/__init__.py
InsurAutoML/base.py
InsurAutoML/constant.py
InsurAutoML/version.py
InsurAutoML/balancing/__init__.py
InsurAutoML/balancing/base.py
InsurAutoML/balancing/mixed_sampling.py
InsurAutoML/balancing/over_sampling.py
InsurAutoML/balancing/under_sampling.py
InsurAutoML/datasets/__init__.py
InsurAutoML/datasets/image.py
InsurAutoML/datasets/tabular.py
InsurAutoML/datasets/text.py
InsurAutoML/encoding/__init__.py
InsurAutoML/encoding/base.py
InsurAutoML/encoding/encoding.py
InsurAutoML/feature_selection/__init__.py
InsurAutoML/feature_selection/autosklearn.py
InsurAutoML/feature_selection/base.py
InsurAutoML/feature_selection/embed.py
InsurAutoML/feature_selection/filter.py
InsurAutoML/feature_selection/hybrid.py
InsurAutoML/feature_selection/sklearn.py
InsurAutoML/feature_selection/wrapper.py
InsurAutoML/hpo/DL.py
InsurAutoML/hpo/ML.py
InsurAutoML/hpo/__init__.py
InsurAutoML/hpo/base.py
InsurAutoML/hpo/ensemble.py
InsurAutoML/hpo/utils.py
InsurAutoML/hyperparameters/__init__.py
InsurAutoML/hyperparameters/_hyperopt/__init__.py
InsurAutoML/hyperparameters/_hyperopt/_balancing_hyperparameter.py
InsurAutoML/hyperparameters/_hyperopt/_classifier_hyperparameter.py
InsurAutoML/hyperparameters/_hyperopt/_encoder_hyperparameter.py
InsurAutoML/hyperparameters/_hyperopt/_feature_selection_hyperparameter.py
InsurAutoML/hyperparameters/_hyperopt/_imputer_hyperparameter.py
InsurAutoML/hyperparameters/_hyperopt/_regressor_hyperparameter.py
InsurAutoML/hyperparameters/_hyperopt/_scaling_hyperparameter.py
InsurAutoML/imputation/__init__.py
InsurAutoML/imputation/base.py
InsurAutoML/imputation/clustering.py
InsurAutoML/imputation/multiple.py
InsurAutoML/imputation/nn.py
InsurAutoML/model/FNN.py
InsurAutoML/model/ML.py
InsurAutoML/model/RNN.py
InsurAutoML/model/__init__.py
InsurAutoML/model/autosklearn.py
InsurAutoML/model/base.py
InsurAutoML/model/clustering.py
InsurAutoML/model/gam.py
InsurAutoML/model/lightgbm.py
InsurAutoML/model/sklearn_classifiers.py
InsurAutoML-0.2.6.dist-info/LICENSE
InsurAutoML-0.2.6.dist-info/METADATA
InsurAutoML-0.2.6.dist-info/WHEEL
InsurAutoML-0.2.6.dist-info/top_level.txt
InsurAutoML-0.2.6.dist-info/RECORD
