Metadata-Version: 2.1
Name: InsurAutoML
Version: 0.2.6
Summary: Automated Machine Learning/AutoML pipeline.
Home-page: https://github.com/PanyiDong/InsurAutoML
Author: Panyi Dong
Author-email: panyid2@illinois.edu
License: MIT
Platform: Linux
Platform: Windows
Platform: MacOS
Requires-Python: >=3.7
License-File: LICENSE
Requires-Dist: setuptools
Requires-Dist: threadpoolctl >2.2.0
Requires-Dist: cython
Requires-Dist: numpy <1.24.0
Requires-Dist: pandas
Requires-Dist: scipy
Requires-Dist: pyarrow
Requires-Dist: fastparquet
Requires-Dist: func-timeout
Requires-Dist: matplotlib
Requires-Dist: seaborn >=0.11.0
Requires-Dist: ray <2.0.0
Requires-Dist: gensim
Requires-Dist: ray[tune]
Requires-Dist: tqdm
Requires-Dist: tensorboardX
Requires-Dist: scikit-learn >=1.2.0
Requires-Dist: redis ; platform_system == "Windows"
Provides-Extra: dev
Requires-Dist: mlflow ; extra == 'dev'
Requires-Dist: lightgbm ; extra == 'dev'
Requires-Dist: xgboost ; extra == 'dev'
Requires-Dist: pygam ; extra == 'dev'
Requires-Dist: flaml ; extra == 'dev'
Requires-Dist: bayesian-optimization ==1.4.0 ; extra == 'dev'
Requires-Dist: colorama ==0.4.4 ; extra == 'dev'
Requires-Dist: nevergrad ; extra == 'dev'
Requires-Dist: optuna ; extra == 'dev'
Requires-Dist: gensim ; extra == 'dev'
Requires-Dist: torch ; extra == 'dev'
Provides-Extra: extended
Requires-Dist: mlflow ; extra == 'extended'
Requires-Dist: lightgbm ; extra == 'extended'
Requires-Dist: xgboost ; extra == 'extended'
Requires-Dist: pygam ; extra == 'extended'
Requires-Dist: flaml ; extra == 'extended'
Requires-Dist: bayesian-optimization ==1.4.0 ; extra == 'extended'
Requires-Dist: colorama ==0.4.4 ; extra == 'extended'
Requires-Dist: nevergrad ; extra == 'extended'
Requires-Dist: hyperopt ; extra == 'extended'
Requires-Dist: optuna ; extra == 'extended'
Provides-Extra: nn
Requires-Dist: gensim ; extra == 'nn'
Requires-Dist: torch ; extra == 'nn'
Provides-Extra: normal
